namedranges/__init__.py
namedranges-0.8.1.dist-info/METADATA
namedranges-0.8.1.dist-info/WHEEL
namedranges-0.8.1.dist-info/licenses/LICENSE
namedranges-0.8.1.dist-info/RECORD
