Metadata-Version: 2.4
Name: namedranges
Version: 0.8.1
Summary: Named ranges with utilities for index reflows
License: MIT
License-File: LICENSE
Author: Chris Czarnecki
Author-email: kjczarne@gmail.com
Requires-Python: >=3.10,<4.0
Classifier: License :: OSI Approved :: MIT License
Classifier: Programming Language :: Python :: 3
Classifier: Programming Language :: Python :: 3.10
Classifier: Programming Language :: Python :: 3.11
Classifier: Programming Language :: Python :: 3.12
Classifier: Programming Language :: Python :: 3.13
Classifier: Programming Language :: Python :: 3.14
